sapientml_core/__init__.py
sapientml_core/adaptation/__init__.py
sapientml_core/adaptation/artifacts/PY310/label_order.json
sapientml_core/adaptation/artifacts/PY311/label_order.json
sapientml_core/adaptation/artifacts/PY39/label_order.json
sapientml_core/adaptation/artifacts/label_order.json
sapientml_core/adaptation/generation/__init__.py
sapientml_core/adaptation/generation/pipeline_template.py
sapientml_core/adaptation/generation/predicate.py
sapientml_core/adaptation/generation/preprocessing_label.py
sapientml_core/adaptation/generation/template_based_adaptation.py
sapientml_core/datastore/localfile/__init__.py
sapientml_core/datastore/localfile/export_modules/sample_dataset.py
sapientml_core/datastore/localfile/export_modules/split_timeseries_dataset.py
sapientml_core/datastore/localfile/generator.py
sapientml_core/datastore/localfile/templates/concat_train_validation.py.jinja
sapientml_core/datastore/localfile/templates/drop_ignore_columns.py.jinja
sapientml_core/datastore/localfile/templates/drop_inf_or_nan_rows.py.jinja
sapientml_core/datastore/localfile/templates/load_localfile.py.jinja
sapientml_core/datastore/localfile/templates/load_localfile_predict.py.jinja
sapientml_core/datastore/localfile/templates/load_localfile_train.py.jinja
sapientml_core/datastore/localfile/templates/set_index.py.jinja
sapientml_core/datastore/localfile/templates/set_validation_as_test.py.jinja
sapientml_core/datastore/localfile/templates/split.py.jinja
sapientml_core/datastore/localfile/templates/subsample.py.jinja
sapientml_core/design/__init__.py
sapientml_core/design/label_util.py
sapientml_core/design/pp_component_groups.py
sapientml_core/design/search_space.py
sapientml_core/enums.py
sapientml_core/explain/AutoEDA.py
sapientml_core/explain/AutoVisualization.py
sapientml_core/explain/code_miner.py
sapientml_core/explain/code_template.py
sapientml_core/explain/main.py
sapientml_core/explain/pipeline_explanation.py
sapientml_core/explain/templates/jupyter_content.json
sapientml_core-0.7.1.dist-info/LICENSE
sapientml_core-0.7.1.dist-info/METADATA
sapientml_core-0.7.1.dist-info/WHEEL
sapientml_core-0.7.1.dist-info/entry_points.txt
sapientml_core-0.7.1.dist-info/RECORD
